<?xml version="1.0" encoding="UTF-8" standalone="yes"?><timezones><timezone><area>Pacific/Tahiti</area><language>de</language><name>Tahiti, Französisch-Polynesien</name><utc_offset>-36000</utc_offset><order>1</order></timezone><timezone><area>Pacific/Marquesas</area><language>de</language><name>Marquesas-Inseln</name><utc_offset>-34200</utc_offset><order>2</order></timezone><timezone><area>Pacific/Gambier</area><language>de</language><name>Gambierinseln</name><utc_offset>-32400</utc_offset><order>3</order></timezone><timezone><area>America/Tijuana</area><language>de</language><name>Clipperton-Insel</name><utc_offset>-28800</utc_offset><order>4</order></timezone><timezone><area>America/Martinique</area><language>de</language><name>Atlantic Standard Time (Karibik)</name><utc_offset>-14400</utc_offset><order>5</order></timezone><timezone><area>America/Cayenne</area><language>de</language><name>Cayenne</name><utc_offset>-10800</utc_offset><order>6</order></timezone><timezone><area>Europe/Paris</area><language>de</language><name>Madrid, Paris</name><utc_offset>3600</utc_offset><order>7</order></timezone><timezone><area>Indian/Mayotte</area><language>de</language><name>Mayotte</name><utc_offset>10800</utc_offset><order>8</order></timezone><timezone><area>Indian/Reunion</area><language>de</language><name>La Réunion</name><utc_offset>14400</utc_offset><order>9</order></timezone><timezone><area>Indian/Kerguelen</area><language>de</language><name>Kerguelen</name><utc_offset>18000</utc_offset><order>10</order></timezone><timezone><area>Pacific/Noumea</area><language>de</language><name>Nouméa</name><utc_offset>39600</utc_offset><order>11</order></timezone><timezone><area>Pacific/Wallis</area><language>de</language><name>Wallis-Inseln</name><utc_offset>43200</utc_offset><order>12</order></timezone></timezones>